audio_purifier/__init__.py
audio_purifier/purifier.py
audio_purifier/utils.py
audio_purifier/assets/silero_vad.onnx
audio_purifier/faster_whisper_original/__init__.py
audio_purifier/faster_whisper_original/audio.py
audio_purifier/faster_whisper_original/utils.py
audio_purifier/faster_whisper_original/vad.py
audio_purifier-0.0.4.dist-info/METADATA
audio_purifier-0.0.4.dist-info/WHEEL
audio_purifier-0.0.4.dist-info/licenses/LICENSE
audio_purifier-0.0.4.dist-info/RECORD
