Metadata-Version: 2.1
Name: audio-purifier
Version: 0.0.4
Summary: Enables silent parts removal from audio, exporting as new files. Inspired by 'faster-whisper'.
Project-URL: Documentation, https://audio-purifier.readthedocs.io/
Project-URL: Homepage, https://github.com/huynguyengl99/audio-purifier
Project-URL: Repository, https://github.com/huynguyengl99/audio-purifier
Author-email: Huy Nguyen <danghuy1999@gmail.com>
License-Expression: MIT
License-File: LICENSE
Classifier: Environment :: Web Environment
Classifier: Intended Audience :: Developers
Classifier: Intended Audience :: Information Technology
Classifier: License :: OSI Approved :: MIT License
Classifier: Operating System :: OS Independent
Classifier: Programming Language :: Python :: 3
Classifier: Programming Language :: Python :: 3 :: Only
Classifier: Programming Language :: Python :: 3.9
Classifier: Programming Language :: Python :: 3.10
Classifier: Programming Language :: Python :: 3.11
Classifier: Topic :: Multimedia :: Sound/Audio :: Conversion
Requires-Python: >=3.9
Requires-Dist: av==10.*
Requires-Dist: numpy<2,>=1.0.0
Requires-Dist: onnxruntime<2,>=1.14
Requires-Dist: scipy<2,>=1.0.0
Provides-Extra: extra
Requires-Dist: pydub<1,>=0.25.1; extra == 'extra'
